paste2/PASTE2.py
paste2/__init__.py
paste2/glmpca.py
paste2/helper.py
paste2/model_selection.py
paste2/projection.py
paste2-1.0.1.dist-info/METADATA
paste2-1.0.1.dist-info/WHEEL
paste2-1.0.1.dist-info/licenses/LICENSE
paste2-1.0.1.dist-info/RECORD
