Metadata-Version: 2.1
Name: paste2
Version: 1.0.1
Summary: Probabilistic Alignment of Spatial Transcriptomics Experiments v.2
Project-URL: Homepage, https://github.com/raphael-group/paste2
Project-URL: Issues, https://github.com/raphael-group/paste2/issues
Author-email: Xinhao Liu <xl5434@princeton.edu>
Maintainer-email: Xinhao Liu <xl5434@princeton.edu>
License: BSD 3-Clause License
License-File: LICENSE
Classifier: License :: OSI Approved :: BSD License
Classifier: Operating System :: OS Independent
Classifier: Programming Language :: Python :: 3
Requires-Python: >=3.8
Requires-Dist: anndata>=0.7.6
Requires-Dist: networkx
Requires-Dist: numpy
Requires-Dist: pot>=0.9.1
Requires-Dist: scanpy>=1.7.2
Requires-Dist: scipy
Requires-Dist: statsmodels
